PySide6/Qt3DAnimation.pyi
PySide6/Qt3DCore.pyi
PySide6/Qt3DExtras.pyi
PySide6/Qt3DInput.pyi
PySide6/Qt3DLogic.pyi
PySide6/Qt3DRender.pyi
PySide6/QtBluetooth.pyi
PySide6/QtCharts.pyi
PySide6/QtConcurrent.pyi
PySide6/QtCore.pyi
PySide6/QtDBus.pyi
PySide6/QtDataVisualization.pyi
PySide6/QtDesigner.pyi
PySide6/QtGraphs.pyi
PySide6/QtGraphsWidgets.pyi
PySide6/QtGui.pyi
PySide6/QtHelp.pyi
PySide6/QtHttpServer.pyi
PySide6/QtLocation.pyi
PySide6/QtMultimedia.pyi
PySide6/QtMultimediaWidgets.pyi
PySide6/QtNetwork.pyi
PySide6/QtNetworkAuth.pyi
PySide6/QtNfc.pyi
PySide6/QtOpenGL.pyi
PySide6/QtOpenGLWidgets.pyi
PySide6/QtPdf.pyi
PySide6/QtPdfWidgets.pyi
PySide6/QtPositioning.pyi
PySide6/QtPrintSupport.pyi
PySide6/QtQml.pyi
PySide6/QtQuick.pyi
PySide6/QtQuick3D.pyi
PySide6/QtQuickControls2.pyi
PySide6/QtQuickTest.pyi
PySide6/QtQuickWidgets.pyi
PySide6/QtRemoteObjects.pyi
PySide6/QtScxml.pyi
PySide6/QtSensors.pyi
PySide6/QtSerialBus.pyi
PySide6/QtSerialPort.pyi
PySide6/QtSpatialAudio.pyi
PySide6/QtSql.pyi
PySide6/QtStateMachine.pyi
PySide6/QtSvg.pyi
PySide6/QtSvgWidgets.pyi
PySide6/QtTest.pyi
PySide6/QtTextToSpeech.pyi
PySide6/QtUiTools.pyi
PySide6/QtWebChannel.pyi
PySide6/QtWebEngineCore.pyi
PySide6/QtWebEngineQuick.pyi
PySide6/QtWebEngineWidgets.pyi
PySide6/QtWebSockets.pyi
PySide6/QtWebView.pyi
PySide6/QtWidgets.pyi
PySide6/QtXml.pyi
PySide6/__feature__.pyi
PySide6/__init__.py
PySide6/_config.py
PySide6/_git_pyside_version.py
PySide6/py.typed
PySide6/examples/examples.pyproject
PySide6/examples/3d/simple3d/simple3d.py
PySide6/examples/3d/simple3d/simple3d.pyproject
PySide6/examples/3d/simple3d/doc/simple3d.png
PySide6/examples/3d/simple3d/doc/simple3d.rst
PySide6/examples/async/eratosthenes/eratosthenes.pyproject
PySide6/examples/async/eratosthenes/eratosthenes_asyncio.py
PySide6/examples/async/eratosthenes/eratosthenes_trio.py
PySide6/examples/async/eratosthenes/requirements_trio.txt
PySide6/examples/async/eratosthenes/doc/eratosthenes.rst
PySide6_Examples-6.8.1.1.dist-info/METADATA
PySide6_Examples-6.8.1.1.dist-info/WHEEL
PySide6_Examples-6.8.1.1.dist-info/top_level.txt
PySide6_Examples-6.8.1.1.dist-info/RECORD
